MANIFEST.in
README.md
setup.py
requirements/base.txt
requirements/dev.txt
trading.datasets_core.egg-info/PKG-INFO
trading.datasets_core.egg-info/SOURCES.txt
trading.datasets_core.egg-info/dependency_links.txt
trading.datasets_core.egg-info/requires.txt
trading.datasets_core.egg-info/top_level.txt
trading/datasets_core/__init__.py
trading/datasets_core/errors.py
trading/datasets_core/exchange/__init__.py
trading/datasets_core/exchange/base.py
trading/datasets_core/exchange/binance.py
trading/datasets_core/exchange/bitmex.py
trading/datasets_core/exchange/bitstamp.py
trading/datasets_core/exchange/ftx.py
trading/datasets_core/metadata/__init__.py
trading/datasets_core/metadata/timeframe.py
trading/datasets_core/metadata/timeframe_unit.py
trading/datasets_core/utils/__init__.py
trading/datasets_core/utils/datetime_utils.py
trading/datasets_core/utils/threading_utils.py
trading/tests/__init__.py
trading/tests/test_init.py
trading/tests/test_exchange/__init__.py
trading/tests/test_exchange/test_base.py
trading/tests/test_exchange/test_binance.py
trading/tests/test_exchange/test_bitmex.py
trading/tests/test_exchange/test_bitstamp.py
trading/tests/test_exchange/test_ftx.py
trading/tests/test_exchange/test_init.py
trading/tests/test_metadata/__init__.py
trading/tests/test_metadata/test_timeframe.py
trading/tests/test_metadata/test_timeframe_unit.py
trading/tests/test_utils/__init__.py
trading/tests/test_utils/test_datetime_utils.py