Metadata-Version: 2.1
Name: trading.datasets-core
Version: 0.6.7
Summary: trading-datasets-core is the Quant Team's wrapper library for CCXT
Home-page: UNKNOWN
Author: SwapooLabs Quantitative Developers
License: UNKNOWN
Platform: UNKNOWN
Requires-Python: >=3.7
